MANIFEST.in
VERSION
distribute_setup.py
setup.py
lib/zrpc/__init__.py
lib/zrpc/client.py
lib/zrpc/concurrency.py
lib/zrpc/exceptions.py
lib/zrpc/loadbal.py
lib/zrpc/multiserver.py
lib/zrpc/object_pool.py
lib/zrpc/registry.py
lib/zrpc/server.py
lib/zrpc.egg-info/PKG-INFO
lib/zrpc.egg-info/SOURCES.txt
lib/zrpc.egg-info/dependency_links.txt
lib/zrpc.egg-info/requires.txt
lib/zrpc.egg-info/top_level.txt