Metadata-Version: 1.0
Name: zrpc
Version: 0.3.1
Summary: Simple ZeroMQ-based RPC.
Home-page: http://github.com/zacharyvoase/zrpc
Author: Zachary Voase
Author-email: z@dvxhouse.com
License: UNKNOWN
Platform: UNKNOWN
